restfulpy/__init__.py
restfulpy/application.py
restfulpy/authentication.py
restfulpy/authorization.py
restfulpy/configuration.py
restfulpy/controllers.py
restfulpy/db.py
restfulpy/exceptions.py
restfulpy/i18n.py
restfulpy/logging_.py
restfulpy/mimetypes_.py
restfulpy/principal.py
restfulpy/taskqueue.py
restfulpy/utils.py
restfulpy/validation.py
restfulpy/cli/__init__.py
restfulpy/cli/admin.py
restfulpy/cli/base.py
restfulpy/cli/dev.py
restfulpy/cli/main.py
restfulpy/cli/migrate.py
restfulpy/cli/serve.py
restfulpy/cli/utils.py
restfulpy/cli/worker.py
restfulpy/jsonpatch/__init__.py
restfulpy/messaging/__init__.py
restfulpy/messaging/models.py
restfulpy/messaging/providers.py
restfulpy/orm/__init__.py
restfulpy/orm/field.py
restfulpy/orm/fulltext_search.py
restfulpy/orm/metadata.py
restfulpy/orm/mixines.py
restfulpy/orm/models.py
restfulpy/testing/__init__.py
restfulpy/testing/constants.py
restfulpy/testing/documentation.py
restfulpy/testing/helpers.py
restfulpy/testing/testcases.py
restfulpy/testing/mockup/__init__.py
restfulpy/testing/mockup/http.py
restfulpy/tests/__init__.py
restfulpy/tests/helpers.py
restfulpy/tests/test_application.py
restfulpy/tests/test_authenticator.py
restfulpy/tests/test_impersonation.py
restfulpy/tests/test_json_payload.py
restfulpy/tests/test_jsonpatch.py
restfulpy/tests/test_orm.py
restfulpy/tests/test_validation.py
restfulpy-0.14.2.dist-info/DESCRIPTION.rst
restfulpy-0.14.2.dist-info/METADATA
restfulpy-0.14.2.dist-info/RECORD
restfulpy-0.14.2.dist-info/WHEEL
restfulpy-0.14.2.dist-info/metadata.json
restfulpy-0.14.2.dist-info/top_level.txt
