Metadata-Version: 2.0
Name: restfulpy
Version: 0.14.2
Summary: A toolchain for developing REST APIs
Home-page: UNKNOWN
Author: Vahid Mardani
Author-email: vahid.mardani@gmail.com
License: UNKNOWN
Platform: UNKNOWN
Requires-Dist: nanohttp (>=0.12.0)
Requires-Dist: argcomplete
Requires-Dist: ujson
Requires-Dist: appdirs
Requires-Dist: sqlalchemy
Requires-Dist: alembic
Requires-Dist: psycopg2
Requires-Dist: itsdangerous
Requires-Dist: mako
Requires-Dist: psycopg2
Requires-Dist: redis
Requires-Dist: requests
Requires-Dist: webtest
Requires-Dist: nose
